decouple/__init__.py
decouple/decouple.py
decouple/py.typed
decouple/version.py
python_decouple_typed-3.11.0.dist-info/LICENSE
python_decouple_typed-3.11.0.dist-info/METADATA
python_decouple_typed-3.11.0.dist-info/WHEEL
python_decouple_typed-3.11.0.dist-info/top_level.txt
python_decouple_typed-3.11.0.dist-info/RECORD
