Metadata-Version: 2.1
Name: python-decouple-typed
Version: 3.11.0
Summary: Typed strict separation of settings from code.
Home-page: https://github.com/kaas-mulvad/python-decouple-typed
Author: Søren Mulvad
Author-email: shmulvad@gmail.com
License: MIT
Platform: any
Classifier: Development Status :: 5 - Production/Stable
Classifier: Framework :: Django
Classifier: Framework :: Flask
Classifier: Intended Audience :: Developers
Classifier: License :: OSI Approved :: MIT License
Classifier: Natural Language :: English
Classifier: Operating System :: OS Independent
Classifier: Programming Language :: Python
Classifier: Programming Language :: Python :: 3
Classifier: Topic :: Software Development :: Libraries
Requires-Python: >=3.8.0
License-File: LICENSE
